[{"path":"/en/how-to-neutralize-network-costs","title":"How to neutralize network costs","date":"2022-10-05T00:00:00.000Z","readingTime":11,"formattedDate":"October 5, 2022","availableLanguages":[{"path":"/ru/how-to-neutralize-network-costs","languageName":"Русский","language":"ru"}],"language":"en"},{"path":"/ru/how-to-neutralize-network-costs","title":"Нейтрализуем издержки сетей","date":"2022-10-05T00:00:00.000Z","readingTime":9,"formattedDate":"5 октября 2022 г.","availableLanguages":[{"path":"/en/how-to-neutralize-network-costs","languageName":"English","language":"en"}],"language":"ru"},{"path":"/en/fluid-interfaces","title":"Fluid interfaces","date":"2022-08-18T00:00:00.000Z","readingTime":5,"formattedDate":"August 18, 2022","availableLanguages":[{"path":"/ru/fluid-interfaces","languageName":"Русский","language":"ru"}],"language":"en"},{"path":"/ru/fluid-interfaces","title":"Резиновые интерфейсы","date":"2022-08-18T00:00:00.000Z","readingTime":5,"formattedDate":"18 августа 2022 г.","availableLanguages":[{"path":"/en/fluid-interfaces","languageName":"English","language":"en"}],"language":"ru"}]